{
  "pcode": 9688, 
  "addresses": [
    {
      "lat": 50.792915911170844, 
      "housenumber": "1", 
      "pcode": 9688, 
      "street": "Neutenstraat", 
      "lon": 3.6732808597542035
    }, 
    {
      "lat": 50.79444120041215, 
      "housenumber": "10", 
      "pcode": 9688, 
      "street": "Neutenstraat", 
      "lon": 3.6706097265175557
    }, 
    {
      "pcode": 9688, 
      "street": "Neutenstraat", 
      "housenumber": "12"
    }, 
    {
      "lat": 50.79358799643379, 
      "housenumber": "2", 
      "pcode": 9688, 
      "street": "Neutenstraat", 
      "lon": 3.671538228037894
    }, 
    {
      "pcode": 9688, 
      "street": "Neutenstraat", 
      "housenumber": "2A"
    }, 
    {
      "pcode": 9688, 
      "street": "Neutenstraat", 
      "housenumber": "2X"
    }, 
    {
      "lat": 50.793384802837956, 
      "housenumber": "3", 
      "pcode": 9688, 
      "street": "Neutenstraat", 
      "lon": 3.671006077828932
    }, 
    {
      "lat": 50.7936866989591, 
      "housenumber": "4", 
      "pcode": 9688, 
      "street": "Neutenstraat", 
      "lon": 3.6711740831849817
    }, 
    {
      "lat": 50.793578766862716, 
      "housenumber": "5", 
      "pcode": 9688, 
      "street": "Neutenstraat", 
      "lon": 3.670470598134079
    }, 
    {
      "lat": 50.79396766106158, 
      "housenumber": "6", 
      "pcode": 9688, 
      "street": "Neutenstraat", 
      "lon": 3.671283820491731
    }, 
    {
      "lat": 50.794686750616144, 
      "housenumber": "7", 
      "pcode": 9688, 
      "street": "Neutenstraat", 
      "lon": 3.6691971638230347
    }, 
    {
      "lat": 50.79417918533191, 
      "housenumber": "8", 
      "pcode": 9688, 
      "street": "Neutenstraat", 
      "lon": 3.671009913883206
    }
  ], 
  "name": "Neutenstraat"
}