{
  "addresses": [
    {
      "housenumber": "1", 
      "lat": 50.854732673999784, 
      "lon": 4.918991189481406, 
      "pcode": 3384, 
      "street": "Uilekotstraat"
    }, 
    {
      "housenumber": "3", 
      "lat": 50.854804255878506, 
      "lon": 4.919885061278377, 
      "pcode": 3384, 
      "street": "Uilekotstraat"
    }, 
    {
      "housenumber": "5", 
      "lat": 50.85473329342445, 
      "lon": 4.920274219239631, 
      "pcode": 3384, 
      "street": "Uilekotstraat"
    }, 
    {
      "housenumber": "7", 
      "lat": 50.8547194586842, 
      "lon": 4.920692167985546, 
      "pcode": 3384, 
      "street": "Uilekotstraat"
    }
  ]
}