{
  "addresses": [
    {
      "housenumber": "1", 
      "lat": 51.04166458284632, 
      "lon": 3.6395375911600905, 
      "pcode": 9031, 
      "street": "Sint-Gerolfstraat"
    }, 
    {
      "housenumber": "11", 
      "lat": 51.04268039372627, 
      "lon": 3.6385077899984584, 
      "pcode": 9031, 
      "street": "Sint-Gerolfstraat"
    }, 
    {
      "housenumber": "14", 
      "lat": 51.042758276409245, 
      "lon": 3.6400242140732275, 
      "pcode": 9031, 
      "street": "Sint-Gerolfstraat"
    }, 
    {
      "housenumber": "16", 
      "lat": 51.043745969346446, 
      "lon": 3.6396215554273925, 
      "pcode": 9031, 
      "street": "Sint-Gerolfstraat"
    }, 
    {
      "housenumber": "2", 
      "lat": 51.041860813883375, 
      "lon": 3.6407726650491914, 
      "pcode": 9031, 
      "street": "Sint-Gerolfstraat"
    }, 
    {
      "housenumber": "3", 
      "lat": 51.042186077695085, 
      "lon": 3.6395261950037363, 
      "pcode": 9031, 
      "street": "Sint-Gerolfstraat"
    }, 
    {
      "housenumber": "30", 
      "lat": 51.04519056088616, 
      "lon": 3.6351575790737636, 
      "pcode": 9031, 
      "street": "Sint-Gerolfstraat"
    }, 
    {
      "housenumber": "32", 
      "lat": 51.04550402928813, 
      "lon": 3.6337732679201724, 
      "pcode": 9031, 
      "street": "Sint-Gerolfstraat"
    }, 
    {
      "housenumber": "33", 
      "lat": 51.0440103539186, 
      "lon": 3.6349283647417305, 
      "pcode": 9031, 
      "street": "Sint-Gerolfstraat"
    }, 
    {
      "housenumber": "34", 
      "lat": 51.04477369528561, 
      "lon": 3.6317085944375096, 
      "pcode": 9031, 
      "street": "Sint-Gerolfstraat"
    }, 
    {
      "housenumber": "35", 
      "lat": 51.04378679009188, 
      "lon": 3.634019523349308, 
      "pcode": 9031, 
      "street": "Sint-Gerolfstraat"
    }, 
    {
      "housenumber": "36", 
      "lat": 51.04485618467397, 
      "lon": 3.631444482179704, 
      "pcode": 9031, 
      "street": "Sint-Gerolfstraat"
    }, 
    {
      "housenumber": "38", 
      "lat": 51.044930151265106, 
      "lon": 3.631240681081706, 
      "pcode": 9031, 
      "street": "Sint-Gerolfstraat"
    }, 
    {
      "housenumber": "4", 
      "lat": 51.04203790022174, 
      "lon": 3.6403789243247875, 
      "pcode": 9031, 
      "street": "Sint-Gerolfstraat"
    }, 
    {
      "housenumber": "40", 
      "lat": 51.04508200226811, 
      "lon": 3.6311289147467516, 
      "pcode": 9031, 
      "street": "Sint-Gerolfstraat"
    }, 
    {
      "housenumber": "40A", 
      "lat": 51.04517856144958, 
      "lon": 3.630972955984021, 
      "pcode": 9031, 
      "street": "Sint-Gerolfstraat"
    }, 
    {
      "housenumber": "42", 
      "lat": 51.045358199061454, 
      "lon": 3.630905813087868, 
      "pcode": 9031, 
      "street": "Sint-Gerolfstraat"
    }, 
    {
      "housenumber": "44", 
      "lat": 51.045494592139335, 
      "lon": 3.630651114276697, 
      "pcode": 9031, 
      "street": "Sint-Gerolfstraat"
    }, 
    {
      "housenumber": "46", 
      "lat": 51.045613897866204, 
      "lon": 3.6305388592729106, 
      "pcode": 9031, 
      "street": "Sint-Gerolfstraat"
    }, 
    {
      "housenumber": "47", 
      "lat": 51.04463245501478, 
      "lon": 3.630570865597047, 
      "pcode": 9031, 
      "street": "Sint-Gerolfstraat"
    }, 
    {
      "housenumber": "48", 
      "lat": 51.0459462891139, 
      "lon": 3.630504245031313, 
      "pcode": 9031, 
      "street": "Sint-Gerolfstraat"
    }, 
    {
      "housenumber": "49", 
      "lat": 51.04512873627863, 
      "lon": 3.6304378410875042, 
      "pcode": 9031, 
      "street": "Sint-Gerolfstraat"
    }, 
    {
      "housenumber": "5", 
      "lat": 51.04230479217328, 
      "lon": 3.639200802521205, 
      "pcode": 9031, 
      "street": "Sint-Gerolfstraat"
    }, 
    {
      "housenumber": "51", 
      "lat": 51.04522569822845, 
      "lon": 3.6303463307683264, 
      "pcode": 9031, 
      "street": "Sint-Gerolfstraat"
    }, 
    {
      "housenumber": "52", 
      "lat": 51.04611455314511, 
      "lon": 3.630171319521411, 
      "pcode": 9031, 
      "street": "Sint-Gerolfstraat"
    }, 
    {
      "housenumber": "53", 
      "lat": 51.04532928851787, 
      "lon": 3.6301792786256684, 
      "pcode": 9031, 
      "street": "Sint-Gerolfstraat"
    }, 
    {
      "housenumber": "54", 
      "lat": 51.04633170689645, 
      "lon": 3.630539669826595, 
      "pcode": 9031, 
      "street": "Sint-Gerolfstraat"
    }, 
    {
      "housenumber": "55", 
      "lat": 51.045432855448745, 
      "lon": 3.6301233140510423, 
      "pcode": 9031, 
      "street": "Sint-Gerolfstraat"
    }, 
    {
      "housenumber": "56", 
      "lat": 51.04638386619428, 
      "lon": 3.6304568493822225, 
      "pcode": 9031, 
      "street": "Sint-Gerolfstraat"
    }, 
    {
      "housenumber": "57", 
      "lat": 51.045524302701146, 
      "lon": 3.629983832044064, 
      "pcode": 9031, 
      "street": "Sint-Gerolfstraat"
    }, 
    {
      "housenumber": "58", 
      "lat": 51.046438533037104, 
      "lon": 3.6304442941471478, 
      "pcode": 9031, 
      "street": "Sint-Gerolfstraat"
    }, 
    {
      "housenumber": "59", 
      "lat": 51.04562025924413, 
      "lon": 3.6297463095295126, 
      "pcode": 9031, 
      "street": "Sint-Gerolfstraat"
    }, 
    {
      "housenumber": "6", 
      "lat": 51.04208317878787, 
      "lon": 3.640621769035613, 
      "pcode": 9031, 
      "street": "Sint-Gerolfstraat"
    }, 
    {
      "housenumber": "60", 
      "lat": 51.046517518266114, 
      "lon": 3.6304105350676896, 
      "pcode": 9031, 
      "street": "Sint-Gerolfstraat"
    }, 
    {
      "housenumber": "61", 
      "lat": 51.04571454473767, 
      "lon": 3.6296294554973967, 
      "pcode": 9031, 
      "street": "Sint-Gerolfstraat"
    }, 
    {
      "housenumber": "63", 
      "lat": 51.04580595674244, 
      "lon": 3.629584804166399, 
      "pcode": 9031, 
      "street": "Sint-Gerolfstraat"
    }, 
    {
      "housenumber": "64", 
      "lat": 51.046912732947476, 
      "lon": 3.629656613707485, 
      "pcode": 9031, 
      "street": "Sint-Gerolfstraat"
    }, 
    {
      "housenumber": "65", 
      "lat": 51.045930990662555, 
      "lon": 3.6295547382546345, 
      "pcode": 9031, 
      "street": "Sint-Gerolfstraat"
    }, 
    {
      "housenumber": "66", 
      "lat": 51.04714122092789, 
      "lon": 3.62949528393438, 
      "pcode": 9031, 
      "street": "Sint-Gerolfstraat"
    }, 
    {
      "housenumber": "67", 
      "lat": 51.04612917802504, 
      "lon": 3.629564445626825, 
      "pcode": 9031, 
      "street": "Sint-Gerolfstraat"
    }, 
    {
      "housenumber": "68", 
      "lat": 51.04730973360606, 
      "lon": 3.6295034630464396, 
      "pcode": 9031, 
      "street": "Sint-Gerolfstraat"
    }, 
    {
      "housenumber": "69", 
      "lat": 51.04621708290744, 
      "lon": 3.6293762452076908, 
      "pcode": 9031, 
      "street": "Sint-Gerolfstraat"
    }, 
    {
      "housenumber": "69A", 
      "lat": 51.04637854537656, 
      "lon": 3.6295646465752895, 
      "pcode": 9031, 
      "street": "Sint-Gerolfstraat"
    }, 
    {
      "housenumber": "7", 
      "lat": 51.04226523797526, 
      "lon": 3.6388085734858238, 
      "pcode": 9031, 
      "street": "Sint-Gerolfstraat"
    }, 
    {
      "housenumber": "70", 
      "lat": 51.04743225363803, 
      "lon": 3.629545595960735, 
      "pcode": 9031, 
      "street": "Sint-Gerolfstraat"
    }, 
    {
      "housenumber": "71", 
      "lat": 51.04664546501679, 
      "lon": 3.6290095442343757, 
      "pcode": 9031, 
      "street": "Sint-Gerolfstraat"
    }, 
    {
      "housenumber": "72", 
      "lat": 51.047461188037566, 
      "lon": 3.6292857327966748, 
      "pcode": 9031, 
      "street": "Sint-Gerolfstraat"
    }, 
    {
      "housenumber": "73", 
      "lat": 51.04672778534794, 
      "lon": 3.6289486345389736, 
      "pcode": 9031, 
      "street": "Sint-Gerolfstraat"
    }, 
    {
      "housenumber": "74", 
      "lat": 51.04755161693192, 
      "lon": 3.6292276893291975, 
      "pcode": 9031, 
      "street": "Sint-Gerolfstraat"
    }, 
    {
      "housenumber": "75", 
      "lat": 51.04680885172763, 
      "lon": 3.6288884574699067, 
      "pcode": 9031, 
      "street": "Sint-Gerolfstraat"
    }, 
    {
      "housenumber": "76", 
      "lat": 51.04769981776854, 
      "lon": 3.629164883096692, 
      "pcode": 9031, 
      "street": "Sint-Gerolfstraat"
    }, 
    {
      "housenumber": "77", 
      "lat": 51.04689306902782, 
      "lon": 3.628843346845207, 
      "pcode": 9031, 
      "street": "Sint-Gerolfstraat"
    }, 
    {
      "housenumber": "78", 
      "lat": 51.0478886690298, 
      "lon": 3.6291336646753796, 
      "pcode": 9031, 
      "street": "Sint-Gerolfstraat"
    }, 
    {
      "housenumber": "79", 
      "lat": 51.047007025663774, 
      "lon": 3.628896023293701, 
      "pcode": 9031, 
      "street": "Sint-Gerolfstraat"
    }, 
    {
      "housenumber": "81", 
      "lat": 51.04708698475065, 
      "lon": 3.628831299796339, 
      "pcode": 9031, 
      "street": "Sint-Gerolfstraat"
    }, 
    {
      "housenumber": "83", 
      "lat": 51.04716596043338, 
      "lon": 3.62876744726228, 
      "pcode": 9031, 
      "street": "Sint-Gerolfstraat"
    }, 
    {
      "housenumber": "85", 
      "lat": 51.04724672483111, 
      "lon": 3.62870214016741, 
      "pcode": 9031, 
      "street": "Sint-Gerolfstraat"
    }, 
    {
      "housenumber": "87", 
      "lat": 51.0473290091811, 
      "lon": 3.6286355253518177, 
      "pcode": 9031, 
      "street": "Sint-Gerolfstraat"
    }, 
    {
      "housenumber": "89", 
      "lat": 51.047411009874224, 
      "lon": 3.6285523721020363, 
      "pcode": 9031, 
      "street": "Sint-Gerolfstraat"
    }, 
    {
      "housenumber": "9", 
      "lat": 51.042479157647556, 
      "lon": 3.6386878857549934, 
      "pcode": 9031, 
      "street": "Sint-Gerolfstraat"
    }, 
    {
      "housenumber": "91", 
      "lat": 51.04750779857224, 
      "lon": 3.6284621396147405, 
      "pcode": 9031, 
      "street": "Sint-Gerolfstraat"
    }, 
    {
      "housenumber": "93", 
      "lat": 51.047619599325316, 
      "lon": 3.6284291413106353, 
      "pcode": 9031, 
      "street": "Sint-Gerolfstraat"
    }, 
    {
      "housenumber": "95", 
      "lat": 51.04783032136529, 
      "lon": 3.6285739836393835, 
      "pcode": 9031, 
      "street": "Sint-Gerolfstraat"
    }
  ]
}