{
  "addresses": [
    {
      "housenumber": "1", 
      "lat": 50.74789344496694, 
      "lon": 5.88067670429936, 
      "pcode": 3793, 
      "street": "Kloosterhofstraat"
    }, 
    {
      "housenumber": "11", 
      "lat": 50.74721038213822, 
      "lon": 5.8807161349255885, 
      "pcode": 3793, 
      "street": "Kloosterhofstraat"
    }, 
    {
      "housenumber": "15", 
      "lat": 50.747232040878544, 
      "lon": 5.879826385482814, 
      "pcode": 3793, 
      "street": "Kloosterhofstraat"
    }, 
    {
      "housenumber": "17", 
      "lat": 50.741969047822785, 
      "lon": 5.869142839863589, 
      "pcode": 3793, 
      "street": "Kloosterhofstraat"
    }, 
    {
      "housenumber": "19", 
      "pcode": 3793, 
      "street": "Kloosterhofstraat"
    }, 
    {
      "housenumber": "21", 
      "lat": 50.7466913082929, 
      "lon": 5.879184181788587, 
      "pcode": 3793, 
      "street": "Kloosterhofstraat"
    }, 
    {
      "housenumber": "24", 
      "lat": 50.74688484331674, 
      "lon": 5.878596434568665, 
      "pcode": 3793, 
      "street": "Kloosterhofstraat"
    }, 
    {
      "housenumber": "25", 
      "lat": 50.746608034047156, 
      "lon": 5.878906571560216, 
      "pcode": 3793, 
      "street": "Kloosterhofstraat"
    }, 
    {
      "housenumber": "3", 
      "lat": 50.74778592049492, 
      "lon": 5.880585098606198, 
      "pcode": 3793, 
      "street": "Kloosterhofstraat"
    }, 
    {
      "housenumber": "30", 
      "lat": 50.74669513597825, 
      "lon": 5.877724292615109, 
      "pcode": 3793, 
      "street": "Kloosterhofstraat"
    }, 
    {
      "housenumber": "31", 
      "lat": 50.74597432399657, 
      "lon": 5.877218921016059, 
      "pcode": 3793, 
      "street": "Kloosterhofstraat"
    }, 
    {
      "housenumber": "32", 
      "lat": 50.745582200591926, 
      "lon": 5.875537772661444, 
      "pcode": 3793, 
      "street": "Kloosterhofstraat"
    }, 
    {
      "housenumber": "34", 
      "lat": 50.746027138754584, 
      "lon": 5.875018581520701, 
      "pcode": 3793, 
      "street": "Kloosterhofstraat"
    }, 
    {
      "housenumber": "35", 
      "lat": 50.74405450277197, 
      "lon": 5.872213893731868, 
      "pcode": 3793, 
      "street": "Kloosterhofstraat"
    }, 
    {
      "housenumber": "37", 
      "lat": 50.74336410242484, 
      "lon": 5.871054334981883, 
      "pcode": 3793, 
      "street": "Kloosterhofstraat"
    }, 
    {
      "housenumber": "39", 
      "lat": 50.74216433468134, 
      "lon": 5.869627182868348, 
      "pcode": 3793, 
      "street": "Kloosterhofstraat"
    }, 
    {
      "housenumber": "40", 
      "lat": 50.74234001586133, 
      "lon": 5.868941532293766, 
      "pcode": 3793, 
      "street": "Kloosterhofstraat"
    }, 
    {
      "housenumber": "41", 
      "lat": 50.74197005888619, 
      "lon": 5.869085055771032, 
      "pcode": 3793, 
      "street": "Kloosterhofstraat"
    }, 
    {
      "housenumber": "43", 
      "lat": 50.74009167421177, 
      "lon": 5.869992032234059, 
      "pcode": 3793, 
      "street": "Kloosterhofstraat"
    }, 
    {
      "housenumber": "45", 
      "lat": 50.73897996183104, 
      "lon": 5.86830935487014, 
      "pcode": 3793, 
      "street": "Kloosterhofstraat"
    }, 
    {
      "housenumber": "47", 
      "lat": 50.73736137170022, 
      "lon": 5.866458031823764, 
      "pcode": 3793, 
      "street": "Kloosterhofstraat"
    }, 
    {
      "housenumber": "7", 
      "lat": 50.7475321586336, 
      "lon": 5.880155179870725, 
      "pcode": 3793, 
      "street": "Kloosterhofstraat"
    }, 
    {
      "housenumber": "9", 
      "lat": 50.74661114060655, 
      "lon": 5.8777044523186035, 
      "pcode": 3793, 
      "street": "Kloosterhofstraat"
    }
  ]
}