{
  "addresses": [
    {
      "housenumber": "1", 
      "lat": 50.928632362272594, 
      "lon": 5.322970739325993, 
      "pcode": 3500, 
      "street": "Jasmijnstraat"
    }, 
    {
      "housenumber": "10", 
      "lat": 50.928979312891485, 
      "lon": 5.32291236320016, 
      "pcode": 3500, 
      "street": "Jasmijnstraat"
    }, 
    {
      "housenumber": "11", 
      "lat": 50.928740565159885, 
      "lon": 5.3225770502854175, 
      "pcode": 3500, 
      "street": "Jasmijnstraat"
    }, 
    {
      "housenumber": "12", 
      "lat": 50.92901582079043, 
      "lon": 5.32284496637086, 
      "pcode": 3500, 
      "street": "Jasmijnstraat"
    }, 
    {
      "housenumber": "13", 
      "lat": 50.928698670521285, 
      "lon": 5.322466520825484, 
      "pcode": 3500, 
      "street": "Jasmijnstraat"
    }, 
    {
      "housenumber": "14", 
      "lat": 50.92904010190618, 
      "lon": 5.322777605170323, 
      "pcode": 3500, 
      "street": "Jasmijnstraat"
    }, 
    {
      "housenumber": "15", 
      "lat": 50.92877045212034, 
      "lon": 5.322417196392745, 
      "pcode": 3500, 
      "street": "Jasmijnstraat"
    }, 
    {
      "housenumber": "16", 
      "lat": 50.92905762359555, 
      "lon": 5.322690190775706, 
      "pcode": 3500, 
      "street": "Jasmijnstraat"
    }, 
    {
      "housenumber": "17", 
      "lat": 50.928785263113504, 
      "lon": 5.322331434285132, 
      "pcode": 3500, 
      "street": "Jasmijnstraat"
    }, 
    {
      "housenumber": "18", 
      "lat": 50.92907867336545, 
      "lon": 5.32262219468255, 
      "pcode": 3500, 
      "street": "Jasmijnstraat"
    }, 
    {
      "housenumber": "19", 
      "lat": 50.92879708125235, 
      "lon": 5.3222488830944705, 
      "pcode": 3500, 
      "street": "Jasmijnstraat"
    }, 
    {
      "housenumber": "2", 
      "lat": 50.928912894820776, 
      "lon": 5.323241894126176, 
      "pcode": 3500, 
      "street": "Jasmijnstraat"
    }, 
    {
      "housenumber": "20", 
      "lat": 50.929098148155184, 
      "lon": 5.322537807232479, 
      "pcode": 3500, 
      "street": "Jasmijnstraat"
    }, 
    {
      "housenumber": "21", 
      "lat": 50.92878930795686, 
      "lon": 5.322154410966733, 
      "pcode": 3500, 
      "street": "Jasmijnstraat"
    }, 
    {
      "housenumber": "22", 
      "lat": 50.92911730792952, 
      "lon": 5.322470057080009, 
      "pcode": 3500, 
      "street": "Jasmijnstraat"
    }, 
    {
      "housenumber": "23", 
      "lat": 50.92880857492258, 
      "lon": 5.322073433709055, 
      "pcode": 3500, 
      "street": "Jasmijnstraat"
    }, 
    {
      "housenumber": "24", 
      "lat": 50.92912888770167, 
      "lon": 5.322383659618372, 
      "pcode": 3500, 
      "street": "Jasmijnstraat"
    }, 
    {
      "housenumber": "25", 
      "lat": 50.928830700847264, 
      "lon": 5.3219946483124625, 
      "pcode": 3500, 
      "street": "Jasmijnstraat"
    }, 
    {
      "housenumber": "26", 
      "lat": 50.92915252780095, 
      "lon": 5.322317707531669, 
      "pcode": 3500, 
      "street": "Jasmijnstraat"
    }, 
    {
      "housenumber": "27", 
      "lat": 50.92885094258669, 
      "lon": 5.321915397779346, 
      "pcode": 3500, 
      "street": "Jasmijnstraat"
    }, 
    {
      "housenumber": "28", 
      "lat": 50.92918687601003, 
      "lon": 5.322239454723445, 
      "pcode": 3500, 
      "street": "Jasmijnstraat"
    }, 
    {
      "housenumber": "29", 
      "lat": 50.928869118059445, 
      "lon": 5.32183596292498, 
      "pcode": 3500, 
      "street": "Jasmijnstraat"
    }, 
    {
      "housenumber": "3", 
      "lat": 50.928637250426924, 
      "lon": 5.322889185562465, 
      "pcode": 3500, 
      "street": "Jasmijnstraat"
    }, 
    {
      "housenumber": "30", 
      "lat": 50.92922726571493, 
      "lon": 5.322181098065461, 
      "pcode": 3500, 
      "street": "Jasmijnstraat"
    }, 
    {
      "housenumber": "31", 
      "lat": 50.92890915546492, 
      "lon": 5.321743458239371, 
      "pcode": 3500, 
      "street": "Jasmijnstraat"
    }, 
    {
      "housenumber": "32", 
      "lat": 50.929249980483384, 
      "lon": 5.322107302908369, 
      "pcode": 3500, 
      "street": "Jasmijnstraat"
    }, 
    {
      "housenumber": "33", 
      "lat": 50.928985061968305, 
      "lon": 5.321374144699197, 
      "pcode": 3500, 
      "street": "Jasmijnstraat"
    }, 
    {
      "housenumber": "34", 
      "lat": 50.92922468189843, 
      "lon": 5.322001093212306, 
      "pcode": 3500, 
      "street": "Jasmijnstraat"
    }, 
    {
      "housenumber": "35", 
      "lat": 50.92903086553226, 
      "lon": 5.321280049487052, 
      "pcode": 3500, 
      "street": "Jasmijnstraat"
    }, 
    {
      "housenumber": "36", 
      "lat": 50.929289821374184, 
      "lon": 5.321928302671383, 
      "pcode": 3500, 
      "street": "Jasmijnstraat"
    }, 
    {
      "housenumber": "37", 
      "lat": 50.92906075211837, 
      "lon": 5.321208675965778, 
      "pcode": 3500, 
      "street": "Jasmijnstraat"
    }, 
    {
      "housenumber": "38", 
      "lat": 50.92930913212656, 
      "lon": 5.321764390660788, 
      "pcode": 3500, 
      "street": "Jasmijnstraat"
    }, 
    {
      "housenumber": "39", 
      "lat": 50.92909296876247, 
      "lon": 5.321138203208466, 
      "pcode": 3500, 
      "street": "Jasmijnstraat"
    }, 
    {
      "housenumber": "4", 
      "lat": 50.928973287022124, 
      "lon": 5.323178113404056, 
      "pcode": 3500, 
      "street": "Jasmijnstraat"
    }, 
    {
      "housenumber": "40", 
      "lat": 50.9293315642768, 
      "lon": 5.3216921542408855, 
      "pcode": 3500, 
      "street": "Jasmijnstraat"
    }, 
    {
      "housenumber": "41", 
      "lat": 50.929128107745605, 
      "lon": 5.321073195379113, 
      "pcode": 3500, 
      "street": "Jasmijnstraat"
    }, 
    {
      "housenumber": "42", 
      "lat": 50.92935458071704, 
      "lon": 5.321614381675067, 
      "pcode": 3500, 
      "street": "Jasmijnstraat"
    }, 
    {
      "housenumber": "43", 
      "lat": 50.929179228254064, 
      "lon": 5.320966404653994, 
      "pcode": 3500, 
      "street": "Jasmijnstraat"
    }, 
    {
      "housenumber": "43A", 
      "lat": 50.92927599561794, 
      "lon": 5.320851294033674, 
      "pcode": 3500, 
      "street": "Jasmijnstraat"
    }, 
    {
      "housenumber": "44", 
      "lat": 50.92942366145349, 
      "lon": 5.321598714898379, 
      "pcode": 3500, 
      "street": "Jasmijnstraat"
    }, 
    {
      "housenumber": "45", 
      "lat": 50.92935358695094, 
      "lon": 5.32078387584333, 
      "pcode": 3500, 
      "street": "Jasmijnstraat"
    }, 
    {
      "housenumber": "46", 
      "lat": 50.92943784856552, 
      "lon": 5.321501131473226, 
      "pcode": 3500, 
      "street": "Jasmijnstraat"
    }, 
    {
      "housenumber": "47", 
      "lat": 50.9294327298289, 
      "lon": 5.320813364853412, 
      "pcode": 3500, 
      "street": "Jasmijnstraat"
    }, 
    {
      "housenumber": "48", 
      "lat": 50.92945654691001, 
      "lon": 5.321423697671085, 
      "pcode": 3500, 
      "street": "Jasmijnstraat"
    }, 
    {
      "housenumber": "49", 
      "lat": 50.929442918864595, 
      "lon": 5.3206876756943355, 
      "pcode": 3500, 
      "street": "Jasmijnstraat"
    }, 
    {
      "housenumber": "5", 
      "lat": 50.9286477819339, 
      "lon": 5.322799069173015, 
      "pcode": 3500, 
      "street": "Jasmijnstraat"
    }, 
    {
      "housenumber": "50", 
      "lat": 50.929513382063185, 
      "lon": 5.32134390898968, 
      "pcode": 3500, 
      "street": "Jasmijnstraat"
    }, 
    {
      "housenumber": "51", 
      "lat": 50.929488138486995, 
      "lon": 5.320643356495531, 
      "pcode": 3500, 
      "street": "Jasmijnstraat"
    }, 
    {
      "housenumber": "53", 
      "lat": 50.92953320369041, 
      "lon": 5.32059590445165, 
      "pcode": 3500, 
      "street": "Jasmijnstraat"
    }, 
    {
      "housenumber": "55", 
      "lat": 50.929610190043775, 
      "lon": 5.32049219793164, 
      "pcode": 3500, 
      "street": "Jasmijnstraat"
    }, 
    {
      "housenumber": "6", 
      "lat": 50.92899118212944, 
      "lon": 5.32310009564899, 
      "pcode": 3500, 
      "street": "Jasmijnstraat"
    }, 
    {
      "housenumber": "7", 
      "lat": 50.928721951287216, 
      "lon": 5.322754630492671, 
      "pcode": 3500, 
      "street": "Jasmijnstraat"
    }, 
    {
      "housenumber": "8", 
      "lat": 50.92900969597874, 
      "lon": 5.323023370715576, 
      "pcode": 3500, 
      "street": "Jasmijnstraat"
    }, 
    {
      "housenumber": "9", 
      "lat": 50.928676111349986, 
      "lon": 5.322631786882022, 
      "pcode": 3500, 
      "street": "Jasmijnstraat"
    }
  ]
}