{
  "pcode": 8970, 
  "addresses": [
    {
      "lat": 50.85356382183842, 
      "housenumber": "1", 
      "pcode": 8970, 
      "street": "Europalaan", 
      "lon": 2.7441610027884784
    }, 
    {
      "lat": 50.85039959693734, 
      "housenumber": "13", 
      "pcode": 8970, 
      "street": "Europalaan", 
      "lon": 2.7408545934677035
    }, 
    {
      "lat": 50.850087591688556, 
      "housenumber": "15", 
      "pcode": 8970, 
      "street": "Europalaan", 
      "lon": 2.7403431234647218
    }, 
    {
      "lat": 50.849867219279766, 
      "housenumber": "17", 
      "pcode": 8970, 
      "street": "Europalaan", 
      "lon": 2.7398712387102977
    }, 
    {
      "lat": 50.849634971478345, 
      "housenumber": "19", 
      "pcode": 8970, 
      "street": "Europalaan", 
      "lon": 2.73941198497628
    }, 
    {
      "lat": 50.84963185466113, 
      "housenumber": "19B", 
      "pcode": 8970, 
      "street": "Europalaan", 
      "lon": 2.7394076898576722
    }, 
    {
      "lat": 50.854432593623095, 
      "housenumber": "2", 
      "pcode": 8970, 
      "street": "Europalaan", 
      "lon": 2.7458892844129608
    }, 
    {
      "lat": 50.8490997312458, 
      "housenumber": "21", 
      "pcode": 8970, 
      "street": "Europalaan", 
      "lon": 2.739207254199116
    }, 
    {
      "lat": 50.85035998053133, 
      "housenumber": "22", 
      "pcode": 8970, 
      "street": "Europalaan", 
      "lon": 2.7433281449456026
    }, 
    {
      "lat": 50.85050310619393, 
      "housenumber": "24", 
      "pcode": 8970, 
      "street": "Europalaan", 
      "lon": 2.7430734925959843
    }, 
    {
      "lat": 50.84881640238517, 
      "housenumber": "27", 
      "pcode": 8970, 
      "street": "Europalaan", 
      "lon": 2.7386828840020425
    }, 
    {
      "pcode": 8970, 
      "street": "Europalaan", 
      "housenumber": "4"
    }, 
    {
      "lat": 50.852961912590736, 
      "housenumber": "5", 
      "pcode": 8970, 
      "street": "Europalaan", 
      "lon": 2.742712901220097
    }, 
    {
      "pcode": 8970, 
      "street": "Europalaan", 
      "housenumber": "5A"
    }, 
    {
      "lat": 50.85292957197944, 
      "housenumber": "5C", 
      "pcode": 8970, 
      "street": "Europalaan", 
      "lon": 2.7426955537445843
    }, 
    {
      "lat": 50.8530890261113, 
      "housenumber": "6", 
      "pcode": 8970, 
      "street": "Europalaan", 
      "lon": 2.745997168576923
    }, 
    {
      "lat": 50.85231333534247, 
      "housenumber": "7", 
      "pcode": 8970, 
      "street": "Europalaan", 
      "lon": 2.7438804940756025
    }
  ], 
  "name": "Europalaan"
}