{
  "pcode": 2381, 
  "addresses": [
    {
      "lat": 51.41277037909477, 
      "housenumber": "1", 
      "pcode": 2381, 
      "street": "Koning Albertstraat", 
      "lon": 5.014751510256956
    }, 
    {
      "lat": 51.41300007526831, 
      "housenumber": "10", 
      "pcode": 2381, 
      "street": "Koning Albertstraat", 
      "lon": 5.013585606601348
    }, 
    {
      "lat": 51.411718091103694, 
      "housenumber": "100", 
      "pcode": 2381, 
      "street": "Koning Albertstraat", 
      "lon": 5.003493287824025
    }, 
    {
      "lat": 51.41130789107219, 
      "housenumber": "101", 
      "pcode": 2381, 
      "street": "Koning Albertstraat", 
      "lon": 5.003138278840543
    }, 
    {
      "lat": 51.41170077062624, 
      "housenumber": "102", 
      "pcode": 2381, 
      "street": "Koning Albertstraat", 
      "lon": 5.002782612332596
    }, 
    {
      "lat": 51.41174268363109, 
      "housenumber": "104", 
      "pcode": 2381, 
      "street": "Koning Albertstraat", 
      "lon": 5.002407197302425
    }, 
    {
      "lat": 51.41181542898904, 
      "housenumber": "106", 
      "pcode": 2381, 
      "street": "Koning Albertstraat", 
      "lon": 5.001913053314554
    }, 
    {
      "lat": 51.40749765025013, 
      "housenumber": "107", 
      "pcode": 2381, 
      "street": "Koning Albertstraat", 
      "lon": 4.990915253551719
    }, 
    {
      "lat": 51.411732740268825, 
      "housenumber": "108", 
      "pcode": 2381, 
      "street": "Koning Albertstraat", 
      "lon": 5.0016266279192
    }, 
    {
      "lat": 51.41112839934649, 
      "housenumber": "109", 
      "pcode": 2381, 
      "street": "Koning Albertstraat", 
      "lon": 5.002196872424411
    }, 
    {
      "lat": 51.412592822715865, 
      "housenumber": "11", 
      "pcode": 2381, 
      "street": "Koning Albertstraat", 
      "lon": 5.013371824900121
    }, 
    {
      "lat": 51.41164308466694, 
      "housenumber": "110", 
      "pcode": 2381, 
      "street": "Koning Albertstraat", 
      "lon": 5.001500362982248
    }, 
    {
      "lat": 51.411018835749054, 
      "housenumber": "111", 
      "pcode": 2381, 
      "street": "Koning Albertstraat", 
      "lon": 5.001573913366414
    }, 
    {
      "lat": 51.411554714113116, 
      "housenumber": "112", 
      "pcode": 2381, 
      "street": "Koning Albertstraat", 
      "lon": 5.001183679526824
    }, 
    {
      "pcode": 2381, 
      "street": "Koning Albertstraat", 
      "housenumber": "114"
    }, 
    {
      "lat": 51.411453301880044, 
      "housenumber": "114A", 
      "pcode": 2381, 
      "street": "Koning Albertstraat", 
      "lon": 5.000868544253664
    }, 
    {
      "lat": 51.41096904053057, 
      "housenumber": "115", 
      "pcode": 2381, 
      "street": "Koning Albertstraat", 
      "lon": 5.000984397266426
    }, 
    {
      "lat": 51.411337178788465, 
      "housenumber": "116", 
      "pcode": 2381, 
      "street": "Koning Albertstraat", 
      "lon": 5.000598339631441
    }, 
    {
      "lat": 51.41090025091266, 
      "housenumber": "117", 
      "pcode": 2381, 
      "street": "Koning Albertstraat", 
      "lon": 5.000804811098479
    }, 
    {
      "pcode": 2381, 
      "street": "Koning Albertstraat", 
      "housenumber": "117a"
    }, 
    {
      "lat": 51.411288827923315, 
      "housenumber": "118", 
      "pcode": 2381, 
      "street": "Koning Albertstraat", 
      "lon": 5.000361253582039
    }, 
    {
      "lat": 51.41079485112185, 
      "housenumber": "119", 
      "pcode": 2381, 
      "street": "Koning Albertstraat", 
      "lon": 5.000816166190991
    }, 
    {
      "pcode": 2381, 
      "street": "Koning Albertstraat", 
      "housenumber": "119A"
    }, 
    {
      "lat": 51.411196466247276, 
      "housenumber": "120", 
      "pcode": 2381, 
      "street": "Koning Albertstraat", 
      "lon": 5.000017069039429
    }, 
    {
      "lat": 51.41066643803708, 
      "housenumber": "121", 
      "pcode": 2381, 
      "street": "Koning Albertstraat", 
      "lon": 5.0004908959692
    }, 
    {
      "lat": 51.41061570686291, 
      "housenumber": "123", 
      "pcode": 2381, 
      "street": "Koning Albertstraat", 
      "lon": 5.0003125636619155
    }, 
    {
      "lat": 51.4110657228517, 
      "housenumber": "124", 
      "pcode": 2381, 
      "street": "Koning Albertstraat", 
      "lon": 4.999605675780344
    }, 
    {
      "lat": 51.410550527661485, 
      "housenumber": "125", 
      "pcode": 2381, 
      "street": "Koning Albertstraat", 
      "lon": 5.000079276779125
    }, 
    {
      "lat": 51.41133202682336, 
      "housenumber": "126", 
      "pcode": 2381, 
      "street": "Koning Albertstraat", 
      "lon": 4.999032817034404
    }, 
    {
      "lat": 51.410422822556114, 
      "housenumber": "129", 
      "pcode": 2381, 
      "street": "Koning Albertstraat", 
      "lon": 4.999671236002912
    }, 
    {
      "lat": 51.412445295696365, 
      "housenumber": "13", 
      "pcode": 2381, 
      "street": "Koning Albertstraat", 
      "lon": 5.013212679136844
    }, 
    {
      "lat": 51.41115741623047, 
      "housenumber": "130", 
      "pcode": 2381, 
      "street": "Koning Albertstraat", 
      "lon": 4.998943347261319
    }, 
    {
      "lat": 51.41033955245367, 
      "housenumber": "131", 
      "pcode": 2381, 
      "street": "Koning Albertstraat", 
      "lon": 4.999476222484892
    }, 
    {
      "lat": 51.4102937859938, 
      "housenumber": "133", 
      "pcode": 2381, 
      "street": "Koning Albertstraat", 
      "lon": 4.999276689235479
    }, 
    {
      "lat": 51.41039030460977, 
      "housenumber": "135", 
      "pcode": 2381, 
      "street": "Koning Albertstraat", 
      "lon": 4.998991563265955
    }, 
    {
      "lat": 51.41066176826532, 
      "housenumber": "138", 
      "pcode": 2381, 
      "street": "Koning Albertstraat", 
      "lon": 4.998478999300676
    }, 
    {
      "lat": 51.41029342517075, 
      "housenumber": "139", 
      "pcode": 2381, 
      "street": "Koning Albertstraat", 
      "lon": 4.998735715679653
    }, 
    {
      "lat": 51.41243879277491, 
      "housenumber": "13B", 
      "pcode": 2381, 
      "street": "Koning Albertstraat", 
      "lon": 5.012920675953606
    }, 
    {
      "pcode": 2381, 
      "street": "Koning Albertstraat", 
      "housenumber": "13a"
    }, 
    {
      "lat": 51.410669289458085, 
      "housenumber": "140", 
      "pcode": 2381, 
      "street": "Koning Albertstraat", 
      "lon": 4.998399766374325
    }, 
    {
      "lat": 51.41010887336571, 
      "housenumber": "141", 
      "pcode": 2381, 
      "street": "Koning Albertstraat", 
      "lon": 4.998504117510939
    }, 
    {
      "lat": 51.41058323142188, 
      "housenumber": "142", 
      "pcode": 2381, 
      "street": "Koning Albertstraat", 
      "lon": 4.998272409653392
    }, 
    {
      "pcode": 2381, 
      "street": "Koning Albertstraat", 
      "housenumber": "143"
    }, 
    {
      "lat": 51.410561082119514, 
      "housenumber": "144", 
      "pcode": 2381, 
      "street": "Koning Albertstraat", 
      "lon": 4.9980765026295
    }, 
    {
      "lat": 51.40994469142306, 
      "housenumber": "145", 
      "pcode": 2381, 
      "street": "Koning Albertstraat", 
      "lon": 4.998329423591581
    }, 
    {
      "lat": 51.41066249507217, 
      "housenumber": "146", 
      "pcode": 2381, 
      "street": "Koning Albertstraat", 
      "lon": 4.997817021611118
    }, 
    {
      "lat": 51.409866802354955, 
      "housenumber": "147", 
      "pcode": 2381, 
      "street": "Koning Albertstraat", 
      "lon": 4.998136212179266
    }, 
    {
      "lat": 51.410455486097284, 
      "housenumber": "148", 
      "pcode": 2381, 
      "street": "Koning Albertstraat", 
      "lon": 4.9975826775343535
    }, 
    {
      "lat": 51.409953707425316, 
      "housenumber": "149", 
      "pcode": 2381, 
      "street": "Koning Albertstraat", 
      "lon": 4.99778211390483
    }, 
    {
      "lat": 51.41241625327049, 
      "housenumber": "15", 
      "pcode": 2381, 
      "street": "Koning Albertstraat", 
      "lon": 5.012701751796871
    }, 
    {
      "lat": 51.410313540468806, 
      "housenumber": "150", 
      "pcode": 2381, 
      "street": "Koning Albertstraat", 
      "lon": 4.997282242969724
    }, 
    {
      "lat": 51.409689013411274, 
      "housenumber": "151", 
      "pcode": 2381, 
      "street": "Koning Albertstraat", 
      "lon": 4.997747768187882
    }, 
    {
      "lat": 51.41014665968816, 
      "housenumber": "154", 
      "pcode": 2381, 
      "street": "Koning Albertstraat", 
      "lon": 4.99705678245835
    }, 
    {
      "lat": 51.409670961829676, 
      "housenumber": "155", 
      "pcode": 2381, 
      "street": "Koning Albertstraat", 
      "lon": 4.99742300409451
    }, 
    {
      "lat": 51.410370850590326, 
      "housenumber": "156", 
      "pcode": 2381, 
      "street": "Koning Albertstraat", 
      "lon": 4.9968134799587665
    }, 
    {
      "lat": 51.41239222217854, 
      "housenumber": "15A", 
      "pcode": 2381, 
      "street": "Koning Albertstraat", 
      "lon": 5.012476051918632
    }, 
    {
      "lat": 51.412930387137244, 
      "housenumber": "16", 
      "pcode": 2381, 
      "street": "Koning Albertstraat", 
      "lon": 5.012880072565277
    }, 
    {
      "lat": 51.4101897993468, 
      "housenumber": "160", 
      "pcode": 2381, 
      "street": "Koning Albertstraat", 
      "lon": 4.99658208019887
    }, 
    {
      "lat": 51.4100134656516, 
      "housenumber": "162", 
      "pcode": 2381, 
      "street": "Koning Albertstraat", 
      "lon": 4.996308348435727
    }, 
    {
      "lat": 51.409683065610736, 
      "housenumber": "163", 
      "pcode": 2381, 
      "street": "Koning Albertstraat", 
      "lon": 4.996138744115045
    }, 
    {
      "lat": 51.40972138027448, 
      "housenumber": "165", 
      "pcode": 2381, 
      "street": "Koning Albertstraat", 
      "lon": 4.99570896491213
    }, 
    {
      "lat": 51.41010427124488, 
      "housenumber": "166", 
      "pcode": 2381, 
      "street": "Koning Albertstraat", 
      "lon": 4.99598045568211
    }, 
    {
      "lat": 51.410137184017714, 
      "housenumber": "168", 
      "pcode": 2381, 
      "street": "Koning Albertstraat", 
      "lon": 4.995416220132605
    }, 
    {
      "lat": 51.41038344299539, 
      "housenumber": "170", 
      "pcode": 2381, 
      "street": "Koning Albertstraat", 
      "lon": 4.994925000025644
    }, 
    {
      "pcode": 2381, 
      "street": "Koning Albertstraat", 
      "housenumber": "171"
    }, 
    {
      "lat": 51.41042480196274, 
      "housenumber": "172", 
      "pcode": 2381, 
      "street": "Koning Albertstraat", 
      "lon": 4.99439436157056
    }, 
    {
      "lat": 51.409711803498276, 
      "housenumber": "173", 
      "pcode": 2381, 
      "street": "Koning Albertstraat", 
      "lon": 4.994544129539904
    }, 
    {
      "lat": 51.41040658121352, 
      "housenumber": "174", 
      "pcode": 2381, 
      "street": "Koning Albertstraat", 
      "lon": 4.994423722530272
    }, 
    {
      "lat": 51.41284619838877, 
      "housenumber": "18", 
      "pcode": 2381, 
      "street": "Koning Albertstraat", 
      "lon": 5.012344946897866
    }, 
    {
      "lat": 51.4096361268029, 
      "housenumber": "181", 
      "pcode": 2381, 
      "street": "Koning Albertstraat", 
      "lon": 4.993998411111136
    }, 
    {
      "lat": 51.40941441687785, 
      "housenumber": "183", 
      "pcode": 2381, 
      "street": "Koning Albertstraat", 
      "lon": 4.993721063001849
    }, 
    {
      "lat": 51.40942766567597, 
      "housenumber": "185", 
      "pcode": 2381, 
      "street": "Koning Albertstraat", 
      "lon": 4.993338805320085
    }, 
    {
      "lat": 51.409960715680796, 
      "housenumber": "186", 
      "pcode": 2381, 
      "street": "Koning Albertstraat", 
      "lon": 4.993173374883205
    }, 
    {
      "lat": 51.40936186020273, 
      "housenumber": "187", 
      "pcode": 2381, 
      "street": "Koning Albertstraat", 
      "lon": 4.993187733084674
    }, 
    {
      "lat": 51.40981021924, 
      "housenumber": "188", 
      "pcode": 2381, 
      "street": "Koning Albertstraat", 
      "lon": 4.992890232228611
    }, 
    {
      "lat": 51.40912925134887, 
      "housenumber": "191", 
      "pcode": 2381, 
      "street": "Koning Albertstraat", 
      "lon": 4.992863248048737
    }, 
    {
      "lat": 51.40896460390363, 
      "housenumber": "193", 
      "pcode": 2381, 
      "street": "Koning Albertstraat", 
      "lon": 4.992724213557476
    }, 
    {
      "lat": 51.40881139306584, 
      "housenumber": "195", 
      "pcode": 2381, 
      "street": "Koning Albertstraat", 
      "lon": 4.992546817699571
    }, 
    {
      "lat": 51.409345142792574, 
      "housenumber": "196", 
      "pcode": 2381, 
      "street": "Koning Albertstraat", 
      "lon": 4.991923214575934
    }, 
    {
      "lat": 51.40919942731802, 
      "housenumber": "196A", 
      "pcode": 2381, 
      "street": "Koning Albertstraat", 
      "lon": 4.991755980873122
    }, 
    {
      "lat": 51.40906797513762, 
      "housenumber": "196B", 
      "pcode": 2381, 
      "street": "Koning Albertstraat", 
      "lon": 4.991611072296881
    }, 
    {
      "lat": 51.40896773564566, 
      "housenumber": "198", 
      "pcode": 2381, 
      "street": "Koning Albertstraat", 
      "lon": 4.991375897830071
    }, 
    {
      "pcode": 2381, 
      "street": "Koning Albertstraat", 
      "housenumber": "1A"
    }, 
    {
      "lat": 51.41308673827521, 
      "housenumber": "2", 
      "pcode": 2381, 
      "street": "Koning Albertstraat", 
      "lon": 5.014540320555305
    }, 
    {
      "lat": 51.412826840325735, 
      "housenumber": "20", 
      "pcode": 2381, 
      "street": "Koning Albertstraat", 
      "lon": 5.012202098312892
    }, 
    {
      "lat": 51.408829364002685, 
      "housenumber": "200", 
      "pcode": 2381, 
      "street": "Koning Albertstraat", 
      "lon": 4.9911964060974805
    }, 
    {
      "lat": 51.40866618984168, 
      "housenumber": "200A", 
      "pcode": 2381, 
      "street": "Koning Albertstraat", 
      "lon": 4.990998905559153
    }, 
    {
      "lat": 51.40847485416974, 
      "housenumber": "200B", 
      "pcode": 2381, 
      "street": "Koning Albertstraat", 
      "lon": 4.990824023300214
    }, 
    {
      "lat": 51.40792859988114, 
      "housenumber": "201", 
      "pcode": 2381, 
      "street": "Koning Albertstraat", 
      "lon": 4.991382356848118
    }, 
    {
      "lat": 51.407761733602285, 
      "housenumber": "201A", 
      "pcode": 2381, 
      "street": "Koning Albertstraat", 
      "lon": 4.991186247077723
    }, 
    {
      "lat": 51.4087721096533, 
      "housenumber": "202", 
      "pcode": 2381, 
      "street": "Koning Albertstraat", 
      "lon": 4.990202553984322
    }, 
    {
      "lat": 51.4081457026842, 
      "housenumber": "202A", 
      "pcode": 2381, 
      "street": "Koning Albertstraat", 
      "lon": 4.9908604240119905
    }, 
    {
      "lat": 51.407678701274676, 
      "housenumber": "203", 
      "pcode": 2381, 
      "street": "Koning Albertstraat", 
      "lon": 4.991028916271903
    }, 
    {
      "lat": 51.40796791504736, 
      "housenumber": "204", 
      "pcode": 2381, 
      "street": "Koning Albertstraat", 
      "lon": 4.990621485600156
    }, 
    {
      "lat": 51.407570725663895, 
      "housenumber": "205", 
      "pcode": 2381, 
      "street": "Koning Albertstraat", 
      "lon": 4.990983204062084
    }, 
    {
      "lat": 51.407821706961094, 
      "housenumber": "206", 
      "pcode": 2381, 
      "street": "Koning Albertstraat", 
      "lon": 4.990530710190115
    }, 
    {
      "pcode": 2381, 
      "street": "Koning Albertstraat", 
      "housenumber": "207"
    }, 
    {
      "lat": 51.407877739853184, 
      "housenumber": "208", 
      "pcode": 2381, 
      "street": "Koning Albertstraat", 
      "lon": 4.990420657709459
    }, 
    {
      "lat": 51.407380822366875, 
      "housenumber": "209", 
      "pcode": 2381, 
      "street": "Koning Albertstraat", 
      "lon": 4.990946453011441
    }, 
    {
      "pcode": 2381, 
      "street": "Koning Albertstraat", 
      "housenumber": "21"
    }, 
    {
      "lat": 51.40792559766469, 
      "housenumber": "210", 
      "pcode": 2381, 
      "street": "Koning Albertstraat", 
      "lon": 4.9902412251368355
    }, 
    {
      "lat": 51.407872266880545, 
      "housenumber": "212", 
      "pcode": 2381, 
      "street": "Koning Albertstraat", 
      "lon": 4.990127263859766
    }, 
    {
      "lat": 51.40782000919953, 
      "housenumber": "214", 
      "pcode": 2381, 
      "street": "Koning Albertstraat", 
      "lon": 4.990014323216377
    }, 
    {
      "lat": 51.407731936818365, 
      "housenumber": "216", 
      "pcode": 2381, 
      "street": "Koning Albertstraat", 
      "lon": 4.98984083091052
    }, 
    {
      "lat": 51.40765109625324, 
      "housenumber": "218", 
      "pcode": 2381, 
      "street": "Koning Albertstraat", 
      "lon": 4.989779532537625
    }, 
    {
      "lat": 51.412818068316646, 
      "housenumber": "22", 
      "pcode": 2381, 
      "street": "Koning Albertstraat", 
      "lon": 5.012112576695751
    }, 
    {
      "lat": 51.40757113633062, 
      "housenumber": "220", 
      "pcode": 2381, 
      "street": "Koning Albertstraat", 
      "lon": 4.989721695284077
    }, 
    {
      "lat": 51.4074800950619, 
      "housenumber": "222", 
      "pcode": 2381, 
      "street": "Koning Albertstraat", 
      "lon": 4.989840476746176
    }, 
    {
      "lat": 51.407427196984024, 
      "housenumber": "224", 
      "pcode": 2381, 
      "street": "Koning Albertstraat", 
      "lon": 4.98995272665056
    }, 
    {
      "lat": 51.4073740284249, 
      "housenumber": "226", 
      "pcode": 2381, 
      "street": "Koning Albertstraat", 
      "lon": 4.990065116390204
    }, 
    {
      "lat": 51.407321926946494, 
      "housenumber": "228", 
      "pcode": 2381, 
      "street": "Koning Albertstraat", 
      "lon": 4.990179675855794
    }, 
    {
      "lat": 51.41233661916591, 
      "housenumber": "23", 
      "pcode": 2381, 
      "street": "Koning Albertstraat", 
      "lon": 5.01217186979066
    }, 
    {
      "lat": 51.407449749390246, 
      "housenumber": "230", 
      "pcode": 2381, 
      "street": "Koning Albertstraat", 
      "lon": 4.990297220834687
    }, 
    {
      "lat": 51.407535024147705, 
      "housenumber": "232", 
      "pcode": 2381, 
      "street": "Koning Albertstraat", 
      "lon": 4.990335585178593
    }, 
    {
      "lat": 51.40762029888948, 
      "housenumber": "234", 
      "pcode": 2381, 
      "street": "Koning Albertstraat", 
      "lon": 4.990373949663398
    }, 
    {
      "lat": 51.41279767585983, 
      "housenumber": "24", 
      "pcode": 2381, 
      "street": "Koning Albertstraat", 
      "lon": 5.012011251839972
    }, 
    {
      "lat": 51.407315674313786, 
      "housenumber": "240", 
      "pcode": 2381, 
      "street": "Koning Albertstraat", 
      "lon": 4.989863424845248
    }, 
    {
      "lat": 51.41241361708567, 
      "housenumber": "25", 
      "pcode": 2381, 
      "street": "Koning Albertstraat", 
      "lon": 5.011845811809181
    }, 
    {
      "lat": 51.41279859159901, 
      "housenumber": "26", 
      "pcode": 2381, 
      "street": "Koning Albertstraat", 
      "lon": 5.011842382125905
    }, 
    {
      "lat": 51.41276859813226, 
      "housenumber": "28", 
      "pcode": 2381, 
      "street": "Koning Albertstraat", 
      "lon": 5.011605387305173
    }, 
    {
      "lat": 51.41225600945839, 
      "housenumber": "29", 
      "pcode": 2381, 
      "street": "Koning Albertstraat", 
      "lon": 5.0115396417552756
    }, 
    {
      "lat": 51.41273367128805, 
      "housenumber": "30", 
      "pcode": 2381, 
      "street": "Koning Albertstraat", 
      "lon": 5.0113664559611415
    }, 
    {
      "lat": 51.412722813146985, 
      "housenumber": "34", 
      "pcode": 2381, 
      "street": "Koning Albertstraat", 
      "lon": 5.011180750776577
    }, 
    {
      "lat": 51.41217969072172, 
      "housenumber": "35", 
      "pcode": 2381, 
      "street": "Koning Albertstraat", 
      "lon": 5.011259608442298
    }, 
    {
      "lat": 51.41270762557863, 
      "housenumber": "36", 
      "pcode": 2381, 
      "street": "Koning Albertstraat", 
      "lon": 5.011047590699913
    }, 
    {
      "lat": 51.412696254551356, 
      "housenumber": "36a", 
      "pcode": 2381, 
      "street": "Koning Albertstraat", 
      "lon": 5.010939923654069
    }, 
    {
      "lat": 51.412684489700084, 
      "housenumber": "36b", 
      "pcode": 2381, 
      "street": "Koning Albertstraat", 
      "lon": 5.010838575301481
    }, 
    {
      "lat": 51.41267202755793, 
      "housenumber": "36c", 
      "pcode": 2381, 
      "street": "Koning Albertstraat", 
      "lon": 5.010733192929421
    }, 
    {
      "lat": 51.4121097188338, 
      "housenumber": "37", 
      "pcode": 2381, 
      "street": "Koning Albertstraat", 
      "lon": 5.0110190452941845
    }, 
    {
      "lat": 51.412655053771935, 
      "housenumber": "38", 
      "pcode": 2381, 
      "street": "Koning Albertstraat", 
      "lon": 5.010631053950697
    }, 
    {
      "lat": 51.412184400583726, 
      "housenumber": "39", 
      "pcode": 2381, 
      "street": "Koning Albertstraat", 
      "lon": 5.010671970723664
    }, 
    {
      "lat": 51.413063744660015, 
      "housenumber": "4", 
      "pcode": 2381, 
      "street": "Koning Albertstraat", 
      "lon": 5.014306294484672
    }, 
    {
      "lat": 51.412631488142345, 
      "housenumber": "40", 
      "pcode": 2381, 
      "street": "Koning Albertstraat", 
      "lon": 5.010451497541436
    }, 
    {
      "lat": 51.4126029088823, 
      "housenumber": "42", 
      "pcode": 2381, 
      "street": "Koning Albertstraat", 
      "lon": 5.010218404754442
    }, 
    {
      "lat": 51.41218623747762, 
      "housenumber": "43", 
      "pcode": 2381, 
      "street": "Koning Albertstraat", 
      "lon": 5.010149689344499
    }, 
    {
      "pcode": 2381, 
      "street": "Koning Albertstraat", 
      "housenumber": "44"
    }, 
    {
      "lat": 51.412146916174216, 
      "housenumber": "45", 
      "pcode": 2381, 
      "street": "Koning Albertstraat", 
      "lon": 5.009575815936469
    }, 
    {
      "lat": 51.41243735775985, 
      "housenumber": "46", 
      "pcode": 2381, 
      "street": "Koning Albertstraat", 
      "lon": 5.009135851294996
    }, 
    {
      "lat": 51.41211407245331, 
      "housenumber": "47", 
      "pcode": 2381, 
      "street": "Koning Albertstraat", 
      "lon": 5.009482945339286
    }, 
    {
      "lat": 51.41202299770112, 
      "housenumber": "47A", 
      "pcode": 2381, 
      "street": "Koning Albertstraat", 
      "lon": 5.0092382132103594
    }, 
    {
      "lat": 51.41176482764528, 
      "housenumber": "49", 
      "pcode": 2381, 
      "street": "Koning Albertstraat", 
      "lon": 5.009211364469033
    }, 
    {
      "lat": 51.41266406286441, 
      "housenumber": "5", 
      "pcode": 2381, 
      "street": "Koning Albertstraat", 
      "lon": 5.014154990020102
    }, 
    {
      "lat": 51.41192456761736, 
      "housenumber": "51", 
      "pcode": 2381, 
      "street": "Koning Albertstraat", 
      "lon": 5.008540928059817
    }, 
    {
      "pcode": 2381, 
      "street": "Koning Albertstraat", 
      "housenumber": "52"
    }, 
    {
      "lat": 51.411849069195874, 
      "housenumber": "53", 
      "pcode": 2381, 
      "street": "Koning Albertstraat", 
      "lon": 5.007974034566424
    }, 
    {
      "pcode": 2381, 
      "street": "Koning Albertstraat", 
      "housenumber": "54"
    }, 
    {
      "lat": 51.41183414317013, 
      "housenumber": "55", 
      "pcode": 2381, 
      "street": "Koning Albertstraat", 
      "lon": 5.0076582051138985
    }, 
    {
      "lat": 49.293335165093566, 
      "housenumber": "58", 
      "pcode": 2381, 
      "street": "Koning Albertstraat", 
      "lon": 2.306689562140502
    }, 
    {
      "lat": 51.411567883366295, 
      "housenumber": "59", 
      "pcode": 2381, 
      "street": "Koning Albertstraat", 
      "lon": 5.006896814865516
    }, 
    {
      "lat": 51.411789509604134, 
      "housenumber": "59a", 
      "pcode": 2381, 
      "street": "Koning Albertstraat", 
      "lon": 5.006649492541238
    }, 
    {
      "lat": 51.41304751374782, 
      "housenumber": "6", 
      "pcode": 2381, 
      "street": "Koning Albertstraat", 
      "lon": 5.0140681945595995
    }, 
    {
      "lat": 51.41225153524979, 
      "housenumber": "60", 
      "pcode": 2381, 
      "street": "Koning Albertstraat", 
      "lon": 5.006440973672435
    }, 
    {
      "lat": 51.41173544598388, 
      "housenumber": "61", 
      "pcode": 2381, 
      "street": "Koning Albertstraat", 
      "lon": 5.006407288754989
    }, 
    {
      "lat": 51.412228340803246, 
      "housenumber": "62", 
      "pcode": 2381, 
      "street": "Koning Albertstraat", 
      "lon": 5.006274792829879
    }, 
    {
      "lat": 51.411674335494155, 
      "housenumber": "63", 
      "pcode": 2381, 
      "street": "Koning Albertstraat", 
      "lon": 5.006221904247337
    }, 
    {
      "lat": 51.41220454558623, 
      "housenumber": "64", 
      "pcode": 2381, 
      "street": "Koning Albertstraat", 
      "lon": 5.006103285973155
    }, 
    {
      "lat": 51.41217519928376, 
      "housenumber": "66", 
      "pcode": 2381, 
      "street": "Koning Albertstraat", 
      "lon": 5.005911006249103
    }, 
    {
      "lat": 51.412558435350064, 
      "housenumber": "7", 
      "pcode": 2381, 
      "street": "Koning Albertstraat", 
      "lon": 5.013745329831338
    }, 
    {
      "lat": 51.41213046894138, 
      "housenumber": "72", 
      "pcode": 2381, 
      "street": "Koning Albertstraat", 
      "lon": 5.005470298036981
    }, 
    {
      "lat": 51.41211452666608, 
      "housenumber": "74", 
      "pcode": 2381, 
      "street": "Koning Albertstraat", 
      "lon": 5.005342592901243
    }, 
    {
      "lat": 51.41210060192789, 
      "housenumber": "76", 
      "pcode": 2381, 
      "street": "Koning Albertstraat", 
      "lon": 5.005190625602854
    }, 
    {
      "lat": 51.4120857192292, 
      "housenumber": "78", 
      "pcode": 2381, 
      "street": "Koning Albertstraat", 
      "lon": 5.0050328961607065
    }, 
    {
      "lat": 51.41302223252506, 
      "housenumber": "8", 
      "pcode": 2381, 
      "street": "Koning Albertstraat", 
      "lon": 5.013824938368592
    }, 
    {
      "lat": 51.41205528375466, 
      "housenumber": "80", 
      "pcode": 2381, 
      "street": "Koning Albertstraat", 
      "lon": 5.004909304339235
    }, 
    {
      "pcode": 2381, 
      "street": "Koning Albertstraat", 
      "housenumber": "81"
    }, 
    {
      "lat": 51.4120191657343, 
      "housenumber": "82", 
      "pcode": 2381, 
      "street": "Koning Albertstraat", 
      "lon": 5.004722394796009
    }, 
    {
      "lat": 51.41198200129627, 
      "housenumber": "86", 
      "pcode": 2381, 
      "street": "Koning Albertstraat", 
      "lon": 5.00452943466694
    }, 
    {
      "lat": 51.41154244190817, 
      "housenumber": "87", 
      "pcode": 2381, 
      "street": "Koning Albertstraat", 
      "lon": 5.004504581361049
    }, 
    {
      "lat": 51.411962377577034, 
      "housenumber": "88", 
      "pcode": 2381, 
      "street": "Koning Albertstraat", 
      "lon": 5.004417633519973
    }, 
    {
      "lat": 51.40936531285567, 
      "housenumber": "89", 
      "pcode": 2381, 
      "street": "Koning Albertstraat", 
      "lon": 4.9928733228855116
    }, 
    {
      "lat": 51.41268925003213, 
      "housenumber": "9", 
      "pcode": 2381, 
      "street": "Koning Albertstraat", 
      "lon": 5.01358933409122
    }, 
    {
      "lat": 51.41194026833406, 
      "housenumber": "90", 
      "pcode": 2381, 
      "street": "Koning Albertstraat", 
      "lon": 5.004283233282368
    }, 
    {
      "lat": 51.41143061288964, 
      "housenumber": "91", 
      "pcode": 2381, 
      "street": "Koning Albertstraat", 
      "lon": 5.004088688341851
    }, 
    {
      "lat": 51.41187504766837, 
      "housenumber": "92", 
      "pcode": 2381, 
      "street": "Koning Albertstraat", 
      "lon": 5.004126252387189
    }, 
    {
      "lat": 51.41144542997198, 
      "housenumber": "93", 
      "pcode": 2381, 
      "street": "Koning Albertstraat", 
      "lon": 5.003688328637895
    }, 
    {
      "lat": 51.411853711147906, 
      "housenumber": "94", 
      "pcode": 2381, 
      "street": "Koning Albertstraat", 
      "lon": 5.003964986243919
    }, 
    {
      "lat": 51.4118055964472, 
      "housenumber": "96", 
      "pcode": 2381, 
      "street": "Koning Albertstraat", 
      "lon": 5.0038361232509905
    }, 
    {
      "lat": 51.411465396393595, 
      "housenumber": "99", 
      "pcode": 2381, 
      "street": "Koning Albertstraat", 
      "lon": 5.0036019355182875
    }
  ], 
  "name": "Koning Albertstraat"
}