{
  "addresses": [
    {
      "housenumber": "1", 
      "lat": 50.905109234787304, 
      "lon": 4.3719934617931075, 
      "pcode": 1800, 
      "street": "Essendallaan"
    }, 
    {
      "housenumber": "10", 
      "lat": 50.90578185194689, 
      "lon": 4.370829697798636, 
      "pcode": 1800, 
      "street": "Essendallaan"
    }, 
    {
      "housenumber": "12", 
      "lat": 50.905621125937216, 
      "lon": 4.3706657645260485, 
      "pcode": 1800, 
      "street": "Essendallaan"
    }, 
    {
      "housenumber": "13", 
      "lat": 50.9052464414992, 
      "lon": 4.37099984423241, 
      "pcode": 1800, 
      "street": "Essendallaan"
    }, 
    {
      "housenumber": "14", 
      "lat": 50.90544538993182, 
      "lon": 4.370379706689918, 
      "pcode": 1800, 
      "street": "Essendallaan"
    }, 
    {
      "housenumber": "15", 
      "lat": 50.90509695215479, 
      "lon": 4.370846433488011, 
      "pcode": 1800, 
      "street": "Essendallaan"
    }, 
    {
      "housenumber": "16", 
      "lat": 50.90524681855685, 
      "lon": 4.370188904187952, 
      "pcode": 1800, 
      "street": "Essendallaan"
    }, 
    {
      "housenumber": "17", 
      "lat": 50.90499124288822, 
      "lon": 4.37059791468108, 
      "pcode": 1800, 
      "street": "Essendallaan"
    }, 
    {
      "housenumber": "18", 
      "lat": 50.905671120452375, 
      "lon": 4.369950785801038, 
      "pcode": 1800, 
      "street": "Essendallaan"
    }, 
    {
      "housenumber": "19", 
      "lat": 50.904846697035474, 
      "lon": 4.370450477407859, 
      "pcode": 1800, 
      "street": "Essendallaan"
    }, 
    {
      "housenumber": "20", 
      "lat": 50.90554769875426, 
      "lon": 4.369807329965575, 
      "pcode": 1800, 
      "street": "Essendallaan"
    }, 
    {
      "housenumber": "21", 
      "lat": 50.90480704682672, 
      "lon": 4.370778175136691, 
      "pcode": 1800, 
      "street": "Essendallaan"
    }, 
    {
      "housenumber": "22", 
      "lat": 50.905394432027165, 
      "lon": 4.369676384902647, 
      "pcode": 1800, 
      "street": "Essendallaan"
    }, 
    {
      "housenumber": "24", 
      "lat": 50.905219410575974, 
      "lon": 4.36957031981632, 
      "pcode": 1800, 
      "street": "Essendallaan"
    }, 
    {
      "housenumber": "26", 
      "lat": 50.90507620666967, 
      "lon": 4.3698137100897565, 
      "pcode": 1800, 
      "street": "Essendallaan"
    }, 
    {
      "housenumber": "28", 
      "lat": 50.90497902804626, 
      "lon": 4.370041746516027, 
      "pcode": 1800, 
      "street": "Essendallaan"
    }, 
    {
      "housenumber": "3", 
      "lat": 50.905209833543566, 
      "lon": 4.371753060227097, 
      "pcode": 1800, 
      "street": "Essendallaan"
    }, 
    {
      "housenumber": "30", 
      "lat": 50.90476499508794, 
      "lon": 4.3698045996690364, 
      "pcode": 1800, 
      "street": "Essendallaan"
    }, 
    {
      "housenumber": "32", 
      "lat": 50.90486855531736, 
      "lon": 4.369606277375363, 
      "pcode": 1800, 
      "street": "Essendallaan"
    }, 
    {
      "housenumber": "34", 
      "lat": 50.90497445253537, 
      "lon": 4.369399850606898, 
      "pcode": 1800, 
      "street": "Essendallaan"
    }, 
    {
      "housenumber": "36", 
      "lat": 50.90450430990006, 
      "lon": 4.36930614839217, 
      "pcode": 1800, 
      "street": "Essendallaan"
    }, 
    {
      "housenumber": "38", 
      "lat": 50.904412795568035, 
      "lon": 4.3695323350862125, 
      "pcode": 1800, 
      "street": "Essendallaan"
    }, 
    {
      "housenumber": "40", 
      "lat": 50.90432496661088, 
      "lon": 4.369746436783312, 
      "pcode": 1800, 
      "street": "Essendallaan"
    }, 
    {
      "housenumber": "42", 
      "lat": 50.904267880597125, 
      "lon": 4.3699783098539235, 
      "pcode": 1800, 
      "street": "Essendallaan"
    }, 
    {
      "housenumber": "44", 
      "lat": 50.90463032874584, 
      "lon": 4.370153191961554, 
      "pcode": 1800, 
      "street": "Essendallaan"
    }, 
    {
      "housenumber": "46", 
      "lat": 50.90453162118848, 
      "lon": 4.370384779650347, 
      "pcode": 1800, 
      "street": "Essendallaan"
    }, 
    {
      "housenumber": "5", 
      "lat": 50.905302520840635, 
      "lon": 4.3715237463553365, 
      "pcode": 1800, 
      "street": "Essendallaan"
    }, 
    {
      "housenumber": "68", 
      "lat": 50.90492502920797, 
      "lon": 4.372379436411847, 
      "pcode": 1800, 
      "street": "Essendallaan"
    }, 
    {
      "housenumber": "7", 
      "lat": 50.905393229937935, 
      "lon": 4.371297701371826, 
      "pcode": 1800, 
      "street": "Essendallaan"
    }, 
    {
      "housenumber": "70", 
      "lat": 50.90506211151383, 
      "lon": 4.3725255996316275, 
      "pcode": 1800, 
      "street": "Essendallaan"
    }, 
    {
      "housenumber": "72", 
      "lat": 50.90522328575008, 
      "lon": 4.372655700820884, 
      "pcode": 1800, 
      "street": "Essendallaan"
    }, 
    {
      "housenumber": "8", 
      "lat": 50.905915788579506, 
      "lon": 4.371027467562986, 
      "pcode": 1800, 
      "street": "Essendallaan"
    }, 
    {
      "housenumber": "9", 
      "lat": 50.90548339951243, 
      "lon": 4.371060850474015, 
      "pcode": 1800, 
      "street": "Essendallaan"
    }
  ]
}