{
  "addresses": [
    {
      "housenumber": "14", 
      "pcode": 9450, 
      "street": "Hoekstraat"
    }, 
    {
      "housenumber": "15", 
      "lat": 50.886627514439475, 
      "lon": 4.023557698705668, 
      "pcode": 9450, 
      "street": "Hoekstraat"
    }, 
    {
      "housenumber": "17", 
      "lat": 50.88687610500815, 
      "lon": 4.023751995844336, 
      "pcode": 9450, 
      "street": "Hoekstraat"
    }, 
    {
      "housenumber": "18", 
      "lat": 50.8866739893985, 
      "lon": 4.023955850324502, 
      "pcode": 9450, 
      "street": "Hoekstraat"
    }, 
    {
      "housenumber": "20", 
      "lat": 50.886936085758165, 
      "lon": 4.024157725155074, 
      "pcode": 9450, 
      "street": "Hoekstraat"
    }, 
    {
      "housenumber": "22", 
      "lat": 50.887022406514, 
      "lon": 4.024195748856311, 
      "pcode": 9450, 
      "street": "Hoekstraat"
    }, 
    {
      "housenumber": "23", 
      "lat": 50.887284971722075, 
      "lon": 4.024097470768376, 
      "pcode": 9450, 
      "street": "Hoekstraat"
    }, 
    {
      "housenumber": "3", 
      "lat": 50.885935494704626, 
      "lon": 4.021783229246883, 
      "pcode": 9450, 
      "street": "Hoekstraat"
    }, 
    {
      "housenumber": "38", 
      "lat": 50.888158162434145, 
      "lon": 4.023100213553905, 
      "pcode": 9450, 
      "street": "Hoekstraat"
    }, 
    {
      "housenumber": "40", 
      "lat": 50.88855250130372, 
      "lon": 4.023671487659605, 
      "pcode": 9450, 
      "street": "Hoekstraat"
    }, 
    {
      "housenumber": "40A", 
      "pcode": 9450, 
      "street": "Hoekstraat"
    }, 
    {
      "housenumber": "42", 
      "lat": 50.888431859674284, 
      "lon": 4.023517460358443, 
      "pcode": 9450, 
      "street": "Hoekstraat"
    }, 
    {
      "housenumber": "5", 
      "lat": 50.88593590829298, 
      "lon": 4.0223199889391195, 
      "pcode": 9450, 
      "street": "Hoekstraat"
    }, 
    {
      "housenumber": "53", 
      "pcode": 9450, 
      "street": "Hoekstraat"
    }, 
    {
      "housenumber": "6", 
      "lat": 50.886830957146074, 
      "lon": 4.024020926446313, 
      "pcode": 9450, 
      "street": "Hoekstraat"
    }, 
    {
      "housenumber": "8", 
      "lat": 50.885931304124064, 
      "lon": 4.02350567569642, 
      "pcode": 9450, 
      "street": "Hoekstraat"
    }
  ]
}